.git_archival.txt
.gitattributes
.gitignore
.gitmodules
.travis.yml
CHANGES.rst
LICENSE.rst
README.rst
pyproject.toml
requirements.txt
setup.py
.github/workflows/linting.yml
.github/workflows/tests.yml
scripts/sf_history_binary_reduction_script.py
umachine_pyio/__init__.py
umachine_pyio/_version.py
umachine_pyio/directory_tree_utils.py
umachine_pyio/index_utils.py
umachine_pyio/load_mock.py
umachine_pyio/memmap_array_utils.py
umachine_pyio/process_ascii_file_into_binaries.py
umachine_pyio/process_ascii_into_memmap.py
umachine_pyio/sf_history_header_processing.py
umachine_pyio.egg-info/PKG-INFO
umachine_pyio.egg-info/SOURCES.txt
umachine_pyio.egg-info/dependency_links.txt
umachine_pyio.egg-info/requires.txt
umachine_pyio.egg-info/top_level.txt
umachine_pyio/example_headers/header_a_0.399872.txt
umachine_pyio/example_headers/header_a_0.668185.txt
umachine_pyio/example_headers/header_a_1.002310.txt
umachine_pyio/example_headers/sfh_ascii_header_column_info.dat
umachine_pyio/tests/__init__.py
umachine_pyio/tests/test_crossmatch.py
umachine_pyio/tests/test_directory_tree_utils.py
umachine_pyio/tests/test_memmap_array_utils.py
umachine_pyio/tests/testing_data/__init__.py