Metadata-Version: 2.1
Name: umachine-pyio
Version: 0.1.0
Summary: Python utilities for I/O associated with UniverseMachine
Author-email: Andrew Hearin <ahearin@anl.gov>
License: BSD 3-Clause License
Project-URL: home, https://github.com/aphearin/umachine_pyio
Classifier: Programming Language :: Python :: 3
Requires-Python: >=3.8
License-File: LICENSE.rst
Requires-Dist: numpy
Requires-Dist: astropy
